[{"name": "Moss giant", "id": 7262, "p": 0, "x": 1685, "y": 10049, "size": 2, "walkingAnimation": 4654, "standingAnimation": 4656, "actions": ["None", "Attack", "None", "None", "None"], "category": 346, "combatLevel": 42, "models": [17456, 17444, 17460]}, {"name": "Moss giant", "id": 7262, "p": 0, "x": 1688, "y": 10050, "size": 2, "walkingAnimation": 4654, "standingAnimation": 4656, "actions": ["None", "Attack", "None", "None", "None"], "category": 346, "combatLevel": 42, "models": [17456, 17444, 17460]}, {"name": "Moss giant", "id": 7262, "p": 0, "x": 1686, "y": 10030, "size": 2, "walkingAnimation": 4654, "standingAnimation": 4656, "actions": ["None", "Attack", "None", "None", "None"], "category": 346, "combatLevel": 42, "models": [17456, 17444, 17460]}, {"name": "Moss giant", "id": 7262, "p": 0, "x": 1687, "y": 10034, "size": 2, "walkingAnimation": 4654, "standingAnimation": 4656, "actions": ["None", "Attack", "None", "None", "None"], "category": 346, "combatLevel": 42, "models": [17456, 17444, 17460]}, {"name": "Moss giant", "id": 7262, "p": 0, "x": 1687, "y": 10044, "size": 2, "walkingAnimation": 4654, "standingAnimation": 4656, "actions": ["None", "Attack", "None", "None", "None"], "category": 346, "combatLevel": 42, "models": [17456, 17444, 17460]}, {"name": "Moss giant", "id": 7262, "p": 0, "x": 1689, "y": 10047, "size": 2, "walkingAnimation": 4654, "standingAnimation": 4656, "actions": ["None", "Attack", "None", "None", "None"], "category": 346, "combatLevel": 42, "models": [17456, 17444, 17460]}, {"name": "Moss giant", "id": 7262, "p": 0, "x": 1690, "y": 10036, "size": 2, "walkingAnimation": 4654, "standingAnimation": 4656, "actions": ["None", "Attack", "None", "None", "None"], "category": 346, "combatLevel": 42, "models": [17456, 17444, 17460]}, {"name": "Moss giant", "id": 7262, "p": 0, "x": 1691, "y": 10030, "size": 2, "walkingAnimation": 4654, "standingAnimation": 4656, "actions": ["None", "Attack", "None", "None", "None"], "category": 346, "combatLevel": 42, "models": [17456, 17444, 17460]}, {"name": "Moss giant", "id": 7262, "p": 0, "x": 1693, "y": 10033, "size": 2, "walkingAnimation": 4654, "standingAnimation": 4656, "actions": ["None", "Attack", "None", "None", "None"], "category": 346, "combatLevel": 42, "models": [17456, 17444, 17460]}, {"name": "Moss giant", "id": 7262, "p": 0, "x": 1419, "y": 9862, "size": 2, "walkingAnimation": 4654, "standingAnimation": 4656, "actions": ["None", "Attack", "None", "None", "None"], "category": 346, "combatLevel": 42, "models": [17456, 17444, 17460]}, {"name": "Moss giant", "id": 7262, "p": 0, "x": 1419, "y": 9869, "size": 2, "walkingAnimation": 4654, "standingAnimation": 4656, "actions": ["None", "Attack", "None", "None", "None"], "category": 346, "combatLevel": 42, "models": [17456, 17444, 17460]}, {"name": "Moss giant", "id": 7262, "p": 0, "x": 1424, "y": 9864, "size": 2, "walkingAnimation": 4654, "standingAnimation": 4656, "actions": ["None", "Attack", "None", "None", "None"], "category": 346, "combatLevel": 42, "models": [17456, 17444, 17460]}, {"name": "Moss giant", "id": 7262, "p": 0, "x": 1425, "y": 9870, "size": 2, "walkingAnimation": 4654, "standingAnimation": 4656, "actions": ["None", "Attack", "None", "None", "None"], "category": 346, "combatLevel": 42, "models": [17456, 17444, 17460]}, {"name": "Moss giant", "id": 7262, "p": 0, "x": 1429, "y": 9862, "size": 2, "walkingAnimation": 4654, "standingAnimation": 4656, "actions": ["None", "Attack", "None", "None", "None"], "category": 346, "combatLevel": 42, "models": [17456, 17444, 17460]}, {"name": "Moss giant", "id": 7262, "p": 0, "x": 1446, "y": 9865, "size": 2, "walkingAnimation": 4654, "standingAnimation": 4656, "actions": ["None", "Attack", "None", "None", "None"], "category": 346, "combatLevel": 42, "models": [17456, 17444, 17460]}, {"name": "Moss giant", "id": 7262, "p": 0, "x": 1452, "y": 9862, "size": 2, "walkingAnimation": 4654, "standingAnimation": 4656, "actions": ["None", "Attack", "None", "None", "None"], "category": 346, "combatLevel": 42, "models": [17456, 17444, 17460]}, {"name": "Moss giant", "id": 7262, "p": 0, "x": 1454, "y": 9866, "size": 2, "walkingAnimation": 4654, "standingAnimation": 4656, "actions": ["None", "Attack", "None", "None", "None"], "category": 346, "combatLevel": 42, "models": [17456, 17444, 17460]}, {"name": "Moss giant", "id": 7262, "p": 0, "x": 1459, "y": 9867, "size": 2, "walkingAnimation": 4654, "standingAnimation": 4656, "actions": ["None", "Attack", "None", "None", "None"], "category": 346, "combatLevel": 42, "models": [17456, 17444, 17460]}, {"name": "Moss giant", "id": 7262, "p": 0, "x": 1460, "y": 9862, "size": 2, "walkingAnimation": 4654, "standingAnimation": 4656, "actions": ["None", "Attack", "None", "None", "None"], "category": 346, "combatLevel": 42, "models": [17456, 17444, 17460]}, {"name": "Moss giant", "id": 7262, "p": 0, "x": 1638, "y": 10017, "size": 2, "walkingAnimation": 4654, "standingAnimation": 4656, "actions": ["None", "Attack", "None", "None", "None"], "category": 346, "combatLevel": 42, "models": [17456, 17444, 17460]}, {"name": "Moss giant", "id": 7262, "p": 0, "x": 1655, "y": 10012, "size": 2, "walkingAnimation": 4654, "standingAnimation": 4656, "actions": ["None", "Attack", "None", "None", "None"], "category": 346, "combatLevel": 42, "models": [17456, 17444, 17460]}, {"name": "Moss giant", "id": 7262, "p": 0, "x": 1658, "y": 10014, "size": 2, "walkingAnimation": 4654, "standingAnimation": 4656, "actions": ["None", "Attack", "None", "None", "None"], "category": 346, "combatLevel": 42, "models": [17456, 17444, 17460]}, {"name": "Moss giant", "id": 7262, "p": 0, "x": 1662, "y": 10014, "size": 2, "walkingAnimation": 4654, "standingAnimation": 4656, "actions": ["None", "Attack", "None", "None", "None"], "category": 346, "combatLevel": 42, "models": [17456, 17444, 17460]}]