[{"name": "Billy Goat", "id": 1794, "p": 0, "x": 3162, "y": 2785, "size": 1, "category": 424, "walkingAnimation": 249, "standingAnimation": 252, "actions": ["None", "Attack", "None", "None", "None"], "combatLevel": 33, "models": [18908]}, {"name": "Billy Goat", "id": 1794, "p": 0, "x": 3175, "y": 2795, "size": 1, "category": 424, "walkingAnimation": 249, "standingAnimation": 252, "actions": ["None", "Attack", "None", "None", "None"], "combatLevel": 33, "models": [18908]}, {"name": "Billy Goat", "id": 1794, "p": 0, "x": 3181, "y": 2763, "size": 1, "category": 424, "walkingAnimation": 249, "standingAnimation": 252, "actions": ["None", "Attack", "None", "None", "None"], "combatLevel": 33, "models": [18908]}, {"name": "Billy Goat", "id": 1794, "p": 0, "x": 3413, "y": 2888, "size": 1, "category": 424, "walkingAnimation": 249, "standingAnimation": 252, "actions": ["None", "Attack", "None", "None", "None"], "combatLevel": 33, "models": [18908]}, {"name": "Billy Goat", "id": 1794, "p": 0, "x": 3364, "y": 3034, "size": 1, "category": 424, "walkingAnimation": 249, "standingAnimation": 252, "actions": ["None", "Attack", "None", "None", "None"], "combatLevel": 33, "models": [18908]}]