[{"name": "Doyen", "id": 8570, "p": 0, "x": 1359, "y": 3713, "size": 1, "walkingAnimation": 819, "rotate180Animation": 820, "rotate90RightAnimation": 821, "rotate90LeftAnimation": 822, "standingAnimation": 808, "combatLevel": 0, "category": 923, "models": [29787, 29811, 29804, 29789, 29797, 29812, 564, 565, 36331], "chatHeadModels": [30958]}, {"name": "Doyen", "id": 8570, "p": 0, "x": 1371, "y": 3693, "size": 1, "walkingAnimation": 819, "rotate180Animation": 820, "rotate90RightAnimation": 821, "rotate90LeftAnimation": 822, "standingAnimation": 808, "combatLevel": 0, "category": 923, "models": [29787, 29811, 29804, 29789, 29797, 29812, 564, 565, 36331], "chatHeadModels": [30958]}, {"name": "Doyen", "id": 8570, "p": 0, "x": 1393, "y": 3682, "size": 1, "walkingAnimation": 819, "rotate180Animation": 820, "rotate90RightAnimation": 821, "rotate90LeftAnimation": 822, "standingAnimation": 808, "combatLevel": 0, "category": 923, "models": [29787, 29811, 29804, 29789, 29797, 29812, 564, 565, 36331], "chatHeadModels": [30958]}]