{
  "id": 21009,
  "name": "Lathe",
  "models_2": [
    21816,
    21815
  ],
  "dim_x": 2,
  "unknown_24": 5744,
  "ambient": 25,
  "contrast": 25,
  "colours": [
    [
      16,
      41147
    ],
    [
      3350,
      41152
    ],
    [
      7446,
      41156
    ],
    [
      6550,
      41160
    ],
    [
      7326,
      41164
    ],
    [
      7585,
      41168
    ]
  ],
  "scale_x": 64,
  "scale_y": 64,
  "scale_z": 64,
  "unknown_78": {
    "unknown_1": 3360,
    "unknown_2": 5
  }
}