{
  "id": 34632,
  "dim_x": 2,
  "dim_y": 2,
  "is_transparent": true,
  "unknown_19": 1,
  "unknown_22": true,
  "unknown_27": false,
  "category": 210,
  "morphs_1": {
    "varbit": 7907,
    "ids": [
      null,
      null,
      null,
      null,
      null,
      null,
      null,
      null,
      null,
      null,
      null,
      null,
      null,
      null,
      null,
      34229,
      34247,
      34265,
      34283,
      null,
      null,
      null,
      null,
      null,
      null,
      34153,
      34171,
      34189,
      null,
      null,
      null,
      null,
      null,
      null,
      34084,
      34102,
      34120,
      34302,
      null,
      null,
      null,
      34283,
      34283,
      34283,
      34283,
      34283,
      34283,
      34283,
      34283,
      34283,
      34283,
      34283,
      34283,
      34283,
      34283,
      34283
    ]
  }
}