[
  {
    "plane": 0,
    "i": 19,
    "j": 19,
    "x": 17,
    "y": 56,
    "id": 21777,
    "type": 0,
    "rotation": 1
  },
  {
    "plane": 0,
    "i": 19,
    "j": 19,
    "x": 24,
    "y": 56,
    "id": 21777,
    "type": 0,
    "rotation": 1
  },
  {
    "plane": 0,
    "i": 19,
    "j": 19,
    "x": 35,
    "y": 56,
    "id": 21777,
    "type": 0,
    "rotation": 1
  },
  {
    "plane": 0,
    "i": 20,
    "j": 20,
    "x": 17,
    "y": 56,
    "id": 21777,
    "type": 0,
    "rotation": 1
  },
  {
    "plane": 0,
    "i": 20,
    "j": 20,
    "x": 24,
    "y": 56,
    "id": 21777,
    "type": 0,
    "rotation": 1
  },
  {
    "plane": 0,
    "i": 20,
    "j": 20,
    "x": 35,
    "y": 56,
    "id": 21777,
    "type": 0,
    "rotation": 1
  },
  {
    "plane": 0,
    "i": 21,
    "j": 19,
    "x": 17,
    "y": 56,
    "id": 21777,
    "type": 0,
    "rotation": 1
  },
  {
    "plane": 0,
    "i": 21,
    "j": 19,
    "x": 24,
    "y": 56,
    "id": 21777,
    "type": 0,
    "rotation": 1
  },
  {
    "plane": 0,
    "i": 21,
    "j": 19,
    "x": 35,
    "y": 56,
    "id": 21777,
    "type": 0,
    "rotation": 1
  }
]