[
  {
    "plane": 0,
    "i": 44,
    "j": 150,
    "x": 20,
    "y": 16,
    "id": 25062,
    "type": 0,
    "rotation": 1
  },
  {
    "plane": 0,
    "i": 44,
    "j": 150,
    "x": 32,
    "y": 25,
    "id": 25062,
    "type": 0,
    "rotation": 0
  },
  {
    "plane": 0,
    "i": 44,
    "j": 150,
    "x": 35,
    "y": 49,
    "id": 25062,
    "type": 9,
    "rotation": 3
  },
  {
    "plane": 0,
    "i": 44,
    "j": 150,
    "x": 49,
    "y": 31,
    "id": 25062,
    "type": 9,
    "rotation": 0
  },
  {
    "plane": 0,
    "i": 47,
    "j": 87,
    "x": 10,
    "y": 51,
    "id": 25062,
    "type": 9,
    "rotation": 1
  },
  {
    "plane": 0,
    "i": 47,
    "j": 87,
    "x": 15,
    "y": 63,
    "id": 25062,
    "type": 0,
    "rotation": 3
  },
  {
    "plane": 0,
    "i": 47,
    "j": 87,
    "x": 44,
    "y": 5,
    "id": 25062,
    "type": 0,
    "rotation": 0
  },
  {
    "plane": 0,
    "i": 47,
    "j": 87,
    "x": 45,
    "y": 22,
    "id": 25062,
    "type": 9,
    "rotation": 3
  }
]