[
  {
    "plane": 0,
    "i": 44,
    "j": 56,
    "x": 43,
    "y": 42,
    "id": 3790,
    "type": 22,
    "rotation": 2
  },
  {
    "plane": 0,
    "i": 44,
    "j": 56,
    "x": 43,
    "y": 43,
    "id": 3790,
    "type": 22,
    "rotation": 1
  },
  {
    "plane": 0,
    "i": 44,
    "j": 56,
    "x": 63,
    "y": 38,
    "id": 3790,
    "type": 22,
    "rotation": 1
  },
  {
    "plane": 0,
    "i": 44,
    "j": 56,
    "x": 63,
    "y": 39,
    "id": 3790,
    "type": 22,
    "rotation": 1
  }
]