[
  {
    "plane": 0,
    "i": 45,
    "j": 81,
    "x": 35,
    "y": 24,
    "id": 42952,
    "type": 22,
    "rotation": 0
  },
  {
    "plane": 0,
    "i": 45,
    "j": 81,
    "x": 40,
    "y": 9,
    "id": 42952,
    "type": 22,
    "rotation": 3
  },
  {
    "plane": 0,
    "i": 45,
    "j": 81,
    "x": 50,
    "y": 29,
    "id": 42952,
    "type": 22,
    "rotation": 1
  },
  {
    "plane": 0,
    "i": 45,
    "j": 81,
    "x": 55,
    "y": 14,
    "id": 42952,
    "type": 22,
    "rotation": 2
  }
]