[
  {
    "plane": 0,
    "i": 47,
    "j": 50,
    "x": 7,
    "y": 30,
    "id": 46293,
    "type": 4,
    "rotation": 3
  },
  {
    "plane": 0,
    "i": 47,
    "j": 50,
    "x": 10,
    "y": 27,
    "id": 46293,
    "type": 4,
    "rotation": 0
  },
  {
    "plane": 0,
    "i": 47,
    "j": 50,
    "x": 15,
    "y": 44,
    "id": 46293,
    "type": 4,
    "rotation": 1
  },
  {
    "plane": 0,
    "i": 47,
    "j": 50,
    "x": 18,
    "y": 54,
    "id": 46293,
    "type": 4,
    "rotation": 3
  },
  {
    "plane": 0,
    "i": 48,
    "j": 50,
    "x": 15,
    "y": 43,
    "id": 46293,
    "type": 4,
    "rotation": 2
  },
  {
    "plane": 0,
    "i": 48,
    "j": 50,
    "x": 21,
    "y": 50,
    "id": 46293,
    "type": 4,
    "rotation": 1
  },
  {
    "plane": 0,
    "i": 48,
    "j": 51,
    "x": 20,
    "y": 0,
    "id": 46293,
    "type": 4,
    "rotation": 1
  },
  {
    "plane": 0,
    "i": 48,
    "j": 51,
    "x": 30,
    "y": 7,
    "id": 46293,
    "type": 4,
    "rotation": 3
  },
  {
    "plane": 0,
    "i": 48,
    "j": 51,
    "x": 31,
    "y": 4,
    "id": 46293,
    "type": 4,
    "rotation": 0
  }
]