[
  {
    "plane": 0,
    "i": 44,
    "j": 66,
    "x": 19,
    "y": 29,
    "id": 46672,
    "type": 10,
    "rotation": 3
  },
  {
    "plane": 0,
    "i": 44,
    "j": 66,
    "x": 19,
    "y": 47,
    "id": 46672,
    "type": 10,
    "rotation": 3
  },
  {
    "plane": 0,
    "i": 44,
    "j": 66,
    "x": 22,
    "y": 44,
    "id": 46672,
    "type": 10,
    "rotation": 3
  },
  {
    "plane": 0,
    "i": 44,
    "j": 66,
    "x": 23,
    "y": 43,
    "id": 46672,
    "type": 10,
    "rotation": 2
  },
  {
    "plane": 0,
    "i": 44,
    "j": 66,
    "x": 29,
    "y": 44,
    "id": 46672,
    "type": 10,
    "rotation": 2
  },
  {
    "plane": 0,
    "i": 44,
    "j": 66,
    "x": 31,
    "y": 23,
    "id": 46672,
    "type": 11,
    "rotation": 2
  },
  {
    "plane": 0,
    "i": 44,
    "j": 66,
    "x": 32,
    "y": 44,
    "id": 46672,
    "type": 10,
    "rotation": 2
  },
  {
    "plane": 0,
    "i": 44,
    "j": 66,
    "x": 33,
    "y": 45,
    "id": 46672,
    "type": 11,
    "rotation": 2
  },
  {
    "plane": 0,
    "i": 44,
    "j": 66,
    "x": 35,
    "y": 23,
    "id": 46672,
    "type": 10,
    "rotation": 3
  },
  {
    "plane": 0,
    "i": 46,
    "j": 155,
    "x": 8,
    "y": 9,
    "id": 46672,
    "type": 10,
    "rotation": 2
  },
  {
    "plane": 0,
    "i": 46,
    "j": 155,
    "x": 9,
    "y": 6,
    "id": 46672,
    "type": 10,
    "rotation": 3
  }
]