[
  {
    "plane": 0,
    "i": 36,
    "j": 99,
    "x": 59,
    "y": 22,
    "id": 47686,
    "type": 3,
    "rotation": 3
  },
  {
    "plane": 0,
    "i": 36,
    "j": 99,
    "x": 59,
    "y": 27,
    "id": 47686,
    "type": 3,
    "rotation": 3
  },
  {
    "plane": 0,
    "i": 37,
    "j": 100,
    "x": 16,
    "y": 4,
    "id": 47686,
    "type": 0,
    "rotation": 0
  },
  {
    "plane": 0,
    "i": 37,
    "j": 100,
    "x": 16,
    "y": 5,
    "id": 47686,
    "type": 0,
    "rotation": 0
  },
  {
    "plane": 0,
    "i": 37,
    "j": 100,
    "x": 16,
    "y": 6,
    "id": 47686,
    "type": 0,
    "rotation": 0
  },
  {
    "plane": 0,
    "i": 37,
    "j": 100,
    "x": 16,
    "y": 7,
    "id": 47686,
    "type": 0,
    "rotation": 0
  },
  {
    "plane": 0,
    "i": 37,
    "j": 100,
    "x": 16,
    "y": 8,
    "id": 47686,
    "type": 0,
    "rotation": 0
  },
  {
    "plane": 0,
    "i": 37,
    "j": 100,
    "x": 16,
    "y": 9,
    "id": 47686,
    "type": 0,
    "rotation": 0
  },
  {
    "plane": 0,
    "i": 37,
    "j": 100,
    "x": 16,
    "y": 10,
    "id": 47686,
    "type": 0,
    "rotation": 0
  },
  {
    "plane": 0,
    "i": 37,
    "j": 100,
    "x": 16,
    "y": 11,
    "id": 47686,
    "type": 0,
    "rotation": 0
  },
  {
    "plane": 0,
    "i": 37,
    "j": 100,
    "x": 16,
    "y": 12,
    "id": 47686,
    "type": 3,
    "rotation": 0
  },
  {
    "plane": 0,
    "i": 37,
    "j": 100,
    "x": 27,
    "y": 11,
    "id": 47686,
    "type": 3,
    "rotation": 3
  },
  {
    "plane": 0,
    "i": 37,
    "j": 100,
    "x": 28,
    "y": 5,
    "id": 47686,
    "type": 3,
    "rotation": 2
  },
  {
    "plane": 0,
    "i": 37,
    "j": 100,
    "x": 28,
    "y": 6,
    "id": 47686,
    "type": 0,
    "rotation": 2
  },
  {
    "plane": 0,
    "i": 37,
    "j": 100,
    "x": 28,
    "y": 7,
    "id": 47686,
    "type": 0,
    "rotation": 2
  },
  {
    "plane": 0,
    "i": 37,
    "j": 100,
    "x": 28,
    "y": 8,
    "id": 47686,
    "type": 0,
    "rotation": 2
  },
  {
    "plane": 0,
    "i": 37,
    "j": 100,
    "x": 28,
    "y": 9,
    "id": 47686,
    "type": 0,
    "rotation": 2
  },
  {
    "plane": 0,
    "i": 37,
    "j": 100,
    "x": 36,
    "y": 5,
    "id": 47686,
    "type": 3,
    "rotation": 2
  },
  {
    "plane": 0,
    "i": 37,
    "j": 100,
    "x": 36,
    "y": 6,
    "id": 47686,
    "type": 0,
    "rotation": 2
  },
  {
    "plane": 0,
    "i": 37,
    "j": 100,
    "x": 36,
    "y": 9,
    "id": 47686,
    "type": 0,
    "rotation": 2
  }
]