[
  {
    "plane": 0,
    "i": 42,
    "j": 76,
    "x": 28,
    "y": 39,
    "id": 6361,
    "type": 22,
    "rotation": 3
  },
  {
    "plane": 0,
    "i": 42,
    "j": 76,
    "x": 33,
    "y": 31,
    "id": 6361,
    "type": 22,
    "rotation": 1
  },
  {
    "plane": 0,
    "i": 54,
    "j": 48,
    "x": 12,
    "y": 15,
    "id": 6361,
    "type": 22,
    "rotation": 3
  },
  {
    "plane": 0,
    "i": 54,
    "j": 48,
    "x": 13,
    "y": 11,
    "id": 6361,
    "type": 22,
    "rotation": 3
  },
  {
    "plane": 0,
    "i": 54,
    "j": 48,
    "x": 24,
    "y": 4,
    "id": 6361,
    "type": 22,
    "rotation": 1
  },
  {
    "plane": 0,
    "i": 54,
    "j": 48,
    "x": 25,
    "y": 18,
    "id": 6361,
    "type": 22,
    "rotation": 0
  },
  {
    "plane": 0,
    "i": 54,
    "j": 48,
    "x": 28,
    "y": 19,
    "id": 6361,
    "type": 22,
    "rotation": 0
  }
]