[
  {
    "plane": 0,
    "i": 46,
    "j": 49,
    "x": 52,
    "y": 41,
    "id": 9162,
    "type": 22,
    "rotation": 3
  },
  {
    "plane": 0,
    "i": 46,
    "j": 49,
    "x": 52,
    "y": 42,
    "id": 9162,
    "type": 22,
    "rotation": 0
  },
  {
    "plane": 0,
    "i": 46,
    "j": 49,
    "x": 55,
    "y": 41,
    "id": 9162,
    "type": 22,
    "rotation": 2
  },
  {
    "plane": 0,
    "i": 46,
    "j": 49,
    "x": 55,
    "y": 42,
    "id": 9162,
    "type": 22,
    "rotation": 1
  }
]